onesignal/__init__.py
onesignal/client.py
onesignal/constants.py
onesignal/decorators.py
onesignal/error.py
onesignal/notification.py
onesignal/request.py
onesignal_sdk-1.1.0.dist-info/LICENSE
onesignal_sdk-1.1.0.dist-info/METADATA
onesignal_sdk-1.1.0.dist-info/WHEEL
onesignal_sdk-1.1.0.dist-info/top_level.txt
onesignal_sdk-1.1.0.dist-info/RECORD
