Metadata-Version: 2.1
Name: onesignal-sdk
Version: 1.1.0
Summary: A Python wrapper around the OneSignal API
Home-page: https://github.com/zeyneloz/onesignal_sdk
Author: Oyku and Zeynel
Author-email: ozdemir.zynl@gmail.com
License: MIT
Keywords: onesignal onesignal-api one-signal push-notification
Platform: UNKNOWN
Classifier: Development Status :: 3 - Alpha
Classifier: Intended Audience :: Developers
Classifier: Topic :: Software Development :: Build Tools
Classifier: License :: OSI Approved :: MIT License
Classifier: Programming Language :: Python :: 3
Classifier: Programming Language :: Python :: 3.3
Classifier: Programming Language :: Python :: 3.4
Classifier: Programming Language :: Python :: 3.5
Classifier: Programming Language :: Python :: 3.6
Classifier: Programming Language :: Python :: 3.7
Classifier: Programming Language :: Python :: 3.8
Provides-Extra: dev
Provides-Extra: test
